savory_pie/__init__.py
savory_pie/auth.py
savory_pie/context.py
savory_pie/errors.py
savory_pie/fields.py
savory_pie/formatters.py
savory_pie/helpers.py
savory_pie/resources.py
savory_pie/savory_newrelic.py
savory_pie/utils.py
savory_pie/django/__init__.py
savory_pie/django/auth.py
savory_pie/django/errors.py
savory_pie/django/fields.py
savory_pie/django/filters.py
savory_pie/django/haystack_field.py
savory_pie/django/haystack_filter.py
savory_pie/django/haystack_resources.py
savory_pie/django/resources.py
savory_pie/django/utils.py
savory_pie/django/validators.py
savory_pie/django/views.py
savory_pie/tests/__init__.py
savory_pie/tests/mock_context.py
savory_pie/tests/test_auth.py
savory_pie/tests/test_fields.py
savory_pie/tests/test_formatters.py
savory_pie/tests/test_helpers.py
savory_pie/tests/test_resource.py
savory_pie/tests/test_savory_newrelic.py
savory_pie/tests/test_utils.py
savory_pie/tests/django/__init__.py
savory_pie/tests/django/dummy_settings.py
savory_pie/tests/django/mock_orm.py
savory_pie/tests/django/mock_request.py
savory_pie/tests/django/search_conf.py
savory_pie/tests/django/test_auth.py
savory_pie/tests/django/test_fields.py
savory_pie/tests/django/test_filters.py
savory_pie/tests/django/test_haystack.py
savory_pie/tests/django/test_integration.py
savory_pie/tests/django/test_m2m_thru.py
savory_pie/tests/django/test_mock_orm.py
savory_pie/tests/django/test_resources.py
savory_pie/tests/django/test_utils.py
savory_pie/tests/django/test_validators.py
savory_pie/tests/django/test_views.py
savory_pie-0.4.11.dist-info/LICENSE
savory_pie-0.4.11.dist-info/METADATA
savory_pie-0.4.11.dist-info/WHEEL
savory_pie-0.4.11.dist-info/top_level.txt
savory_pie-0.4.11.dist-info/RECORD
