Metadata-Version: 2.1
Name: savory-pie
Version: 0.4.11
Summary: A RESTful api libary with support for django
Home-page: https://github.com/RueLaLa/savory-pie
Author: UNKNOWN
Author-email: UNKNOWN
License: MIT
Platform: UNKNOWN
Classifier: Development Status :: 3 - Alpha
Classifier: Environment :: Web Environment
Classifier: Framework :: Django
Classifier: Intended Audience :: Developers
Classifier: License :: OSI Approved :: MIT License
Classifier: Operating System :: OS Independent
Classifier: Programming Language :: Python
Classifier: Programming Language :: Python :: 2
Classifier: Programming Language :: Python :: 2.7
Classifier: Topic :: Software Development :: Libraries :: Python Modules
Requires-Dist: future
Requires-Dist: pytz
Requires-Dist: python-dateutil
